umk/__init__.py
umk/application/__init__.py
umk/application/cmd/__init__.py
umk/application/cmd/config.py
umk/application/cmd/remote.py
umk/application/cmd/root.py
umk/application/cmd/target.py
umk/application/printers.py
umk/application/utils.py
umk/core/__init__.py
umk/core/errors.py
umk/core/globals.py
umk/core/properties.py
umk/core/serialization.py
umk/core/typings.py
umk/entrypoint.py
umk/framework/__init__.py
umk/framework/adapters/__init__.py
umk/framework/adapters/delve.py
umk/framework/adapters/docker/__init__.py
umk/framework/adapters/docker/compose.py
umk/framework/adapters/docker/file.py
umk/framework/adapters/git.py
umk/framework/adapters/go/__init__.py
umk/framework/adapters/go/base.py
umk/framework/filesystem/__init__.py
umk/framework/filesystem/copy.py
umk/framework/filesystem/factories.py
umk/framework/filesystem/installer.py
umk/framework/filesystem/move.py
umk/framework/project/__init__.py
umk/framework/project/base.py
umk/framework/project/golang.py
umk/framework/remote/__init__.py
umk/framework/remote/docker.py
umk/framework/remote/interface.py
umk/framework/remote/ssh.py
umk/framework/system/__init__.py
umk/framework/system/environs.py
umk/framework/system/platform.py
umk/framework/system/shell.py
umk/framework/system/user.py
umk/framework/target/__init__.py
umk/framework/target/golang.py
umk/framework/target/interface.py
umk/framework/target/packages.py
umk/framework/utils/__init__.py
umk/framework/utils/cli.py
umk/framework/utils/code.py
umk/kit/__init__.py
umk/kit/adapter/__init__.py
umk/kit/adapter/docker/__init__.py
umk/kit/adapter/go/__init__.py
umk/kit/config/__init__.py
umk/kit/filesystem/__init__.py
umk/kit/project/__init__.py
umk/kit/remote/__init__.py
umk/kit/system/__init__.py
umk/kit/target/__init__.py
umk/runtime/__init__.py
umk/runtime/config.py
umk/runtime/container.py
umk/runtime/errors.py
umk/runtime/project.py
umk/runtime/remotes.py
umk/runtime/targets.py
umk/runtime/utils.py
umk/state.py
umk-0.1.3.dist-info/LICENSE
umk-0.1.3.dist-info/METADATA
umk-0.1.3.dist-info/WHEEL
umk-0.1.3.dist-info/entry_points.txt
umk-0.1.3.dist-info/RECORD
