Metadata-Version: 2.1
Name: umk
Version: 0.1.3
Summary: Unimake is a set of development tools and frameworks for project maintaining. This tools makes it easy to organize development routines (such as building, testing, linting, running, etc)
License: GPL-3.0-only
Author: Edward Sarkisyan
Author-email: edw.sarkisyan@gmail.com
Requires-Python: >=3.10,<3.12
Classifier: Environment :: Console
Classifier: Intended Audience :: Developers
Classifier: License :: OSI Approved :: GNU General Public License v3 (GPLv3)
Classifier: Operating System :: MacOS
Classifier: Operating System :: POSIX :: Linux
Classifier: Programming Language :: Python :: 3
Classifier: Programming Language :: Python :: 3.10
Classifier: Programming Language :: Python :: 3.11
Classifier: Programming Language :: Python :: 3.12
Requires-Dist: anyio (>=4.0.0,<5.0.0)
Requires-Dist: asyncclick (>=8.1,<9.0)
Requires-Dist: beartype (>=0.16.3,<0.17.0)
Requires-Dist: fs (>=2.4.16,<3.0.0)
Requires-Dist: gitpython (>=3.1.37,<4.0.0)
Requires-Dist: multimethod (>=1.10,<2.0)
Requires-Dist: paramiko (>=3.3.1,<4.0.0)
Requires-Dist: pydantic (>=2.5.3,<3.0.0)
Requires-Dist: python-dotenv (>=1.0.1,<2.0.0)
Requires-Dist: python-on-whales (>=0.69.0,<0.70.0)
Requires-Dist: pyyaml (>=6.0.1,<7.0.0)
Requires-Dist: rich (>=13.6.0,<14.0.0)
